<?xml version="1.0" encoding="utf-8"?>
<openerp>
    <data>
        <record id="product_product_form_add_replacements" model="ir.ui.view">
            <field name="name">product.product.form</field>
            <field name="model">product.product</field>
            <field name="inherit_id" ref="product.product_normal_form_view"/>
            <field name="arch" type="xml">
                <notebook position="inside">
                    <page string="Replacements">
                        <group>
                            <field name="replacement_for_ids" context="{'default_product_id': active_id}">
                                <tree>
                                    <field name="disassembly_ref"/>
                                    <field name="replacement_for_ids"/>
                                    <field name="qty"/>
                                </tree>
                                <form>
                                    <group>
                                        <group>
                                            <field name="disassembly_ref"/>
                                            <field name="product_id" invisible="1"/>
                                            <field name="qty"/>
                                            <field name="replacement_for_ids"/>
                                        </group>
                                    </group>
                                </form>
                            </field>
                            <field name="replacement_ids">
                                <tree>
                                    <field name="disassembly_ref"/>
                                    <field name="product_id"/>
                                    <field name="qty"/>
                                </tree>
                                <form>
                                    <group>
                                        <group>
                                            <field name="disassembly_ref"/>
                                            <field name="product_id"/>
                                            <field name="replacement_for_ids" invisible="1"/>
                                        </group>
                                        <group>
                                            <field name="qty"/>
                                        </group>
                                    </group>
                                </form>
                            </field>
                        </group>
                    </page>
                </notebook>
            </field>
        </record>

        <record id="product_replacement_tree" model="ir.ui.view">
            <field name="name">product.replacement.tree</field>
            <field name="model">product.replacement</field>
            <field name="type">tree</field>
            <field name="arch" type="xml">
                <tree string="Replacements">
                    <field name="disassembly_ref"/>
                    <field name="product_id"/>
                    <field name="qty"/>
                </tree>
            </field>
        </record>

        <record id="product_replacement_form" model="ir.ui.view">
            <field name="name">product.replacement.form</field>
            <field name="model">product.replacement</field>
            <field name="type">form</field>
            <field name="arch" type="xml">
                <form string="Replacement">
                    <group>
                        <field name="disassembly_ref"/>
                        <field name="product_id"/>
                        <field name="qty"/>
                        <field name="replacement_for_ids"/>
                    </group>
                </form>
            </field>
        </record>

        <record id="product_replacement_filter" model="ir.ui.view">
            <field name="name">product.replacement.search</field>
            <field name="model">product.replacement</field>
            <field name="type">search</field>
            <field name="arch" type="xml">
                <search string="Replacement">
                   <field name="disassembly_ref"/>
                    <field name="product_id"/>
               </search>
            </field>
        </record>

        <record model="ir.actions.act_window" id="action_product_replacement">
            <field name="name">Replacements</field>
            <field name="res_model">product.replacement</field>
            <field name="view_type">form</field>
            <field name="view_mode">tree,form</field>
            <field name="view_id" ref="product_replacement_tree"/>
            <field name="search_view_id" ref="product_replacement_filter"/>
        </record>

        <!--TODO: Migrar<menuitem name="Replacements" parent="base.menu_product" action="action_product_replacement" id="product_replacement_menu"/>-->

    </data>
</openerp>
